ErrorFieldConcordance/ErrorFieldConcordance.py
ErrorFieldConcordance/__init__.py
errorfieldconcordance-1.1.dist-info/licenses/LICENSE
errorfieldconcordance-1.1.dist-info/METADATA
errorfieldconcordance-1.1.dist-info/WHEEL
errorfieldconcordance-1.1.dist-info/top_level.txt
errorfieldconcordance-1.1.dist-info/RECORD
