Metadata-Version: 2.4
Name: ErrorFieldConcordance
Version: 1.1
Summary: Calculation of trending concordance between two measures using the Error Field method
Author-email: Joe Rinehart <joerinehartmd@gmail.com>
Keywords: statistics,method comparison,cardiac output,concordance,trending
Classifier: Programming Language :: Python :: 3
Classifier: License :: OSI Approved :: MIT License
Classifier: Operating System :: OS Independent
Requires-Python: >3.0
License-File: LICENSE
Requires-Dist: numpy
Requires-Dist: matplotlib
Dynamic: license-file
